Metadata-Version: 2.3
Name: mkdocstrings-matlab-r2024b
Version: 0.1.2
Summary: Add your description here
Project-URL: Documentation, http://watermarkhu.nl/mkdocstrings-matlab/
Project-URL: Repository, https://github.com/watermarkhu/mkdocstrings-matlab
Project-URL: Issues, https://github.com/watermarkhu/mkdocstrings-matlab/issues
Author-email: Mark Shui Hu <watermarkhu@gmail.com>
License: MIT License
License-File: LICENSE
Keywords: docstring,documentation,matlab,mkdocs,mkdocstrings
Classifier: Development Status :: 3 - Alpha
Classifier: Intended Audience :: Developers
Classifier: License :: OSI Approved :: MIT License
Classifier: Programming Language :: Python :: 3
Classifier: Programming Language :: Python :: 3.9
Classifier: Programming Language :: Python :: 3.10
Classifier: Programming Language :: Python :: 3.11
Classifier: Programming Language :: Python :: 3.12
Classifier: Topic :: Software Development :: Documentation
Requires-Python: <3.13,>=3.9
Requires-Dist: matlabengine==24.2.1
